mcp_local_context/__init__.py
mcp_local_context/cli.py
mcp_local_context/server.py
mcp_local_context-0.1.1.dist-info/licenses/LICENSE
mcp_local_context-0.1.1.dist-info/METADATA
mcp_local_context-0.1.1.dist-info/WHEEL
mcp_local_context-0.1.1.dist-info/top_level.txt
mcp_local_context-0.1.1.dist-info/RECORD
