Metadata-Version: 2.4
Name: mcp-local-context
Version: 0.1.1
Summary: Local Documentation MCP Server with RAG
Home-page: https://github.com/steedmonteiro/mcp-local-context
Author: Steed Monteiro
Author-email: steed.monteiro@gmail.com
Requires-Python: >=3.10
License-File: LICENSE
Requires-Dist: mcp[cli]>=1.9.1
Requires-Dist: vlite>=0.1.0
Dynamic: author
Dynamic: author-email
Dynamic: home-page
Dynamic: license-file
Dynamic: requires-python
